{"location_id":"NOTEBOOK","customer_index":"10","customer_activity":"p","dialogs":[{"first":"SALESMAN","phase":"1","description":"﻿Приветствие, вступление в контакт","dialog":[{"phase":"1","type":"1","salesman":"V4","customer":"W4","next":"NEXT"},{"phase":"1","type":"0","salesman":"AD4","customer":"AC4","next":"NEXT"},{"phase":"1","type":"1","salesman":"R4","customer":"W4","next":"NEXT"},{"phase":"1","type":"0","salesman":"AF4","customer":"AC4","next":"NEXT"}]},{"first":"SALESMAN","phase":"0","description":"﻿Обращение внимания на акции, если не идет на контакт, шаг 1","dialog":[{"phase":"0","type":"1","salesman":"V5","customer":"S5","next":"NEXT"},{"phase":"0","type":"0","salesman":"AD5","customer":"AE5","next":"NEXT"},{"phase":"0","type":"1","salesman":"R5","customer":"S5","next":"NEXT"},{"phase":"0","type":"0","salesman":"AF5","customer":"AE5","next":"NEXT"}]},{"first":"SALESMAN","phase":"0","description":"﻿Обращение внимания на акции, если не идет на контакт, шаг 2 (2 минуты спустя)","dialog":[{"phase":"0","type":"1","salesman":"V6","customer":"W6","next":"NEXT"},{"phase":"0","type":"0","salesman":"AD6","customer":"AE6","next":"NEXT"},{"phase":"0","type":"1","salesman":"T6","customer":"W6","next":"NEXT"},{"phase":"0","type":"0","salesman":"AF6","customer":"AE6","next":"NEXT"}]},{"first":"SALESMAN","phase":"2","description":"﻿Выявление и формирование потребностей","dialog":[{"phase":"2","type":"1","salesman":"V8","customer":"Y8","next":"NEXT"},{"phase":"2","type":"0","salesman":"AD8","customer":"AE8","next":"NEXT"},{"phase":"2","type":"1","salesman":"X8","customer":"Y8","next":"NEXT"},{"phase":"2","type":"0","salesman":"AF8","customer":"AG8","next":"NEXT"},{"phase":"2","type":"1","salesman":"V9","customer":"W9","next":"NEXT"},{"phase":"2","type":"0","salesman":"AD9","customer":"AE9","next":"NEXT"},{"phase":"2","type":"1","salesman":"V10","customer":"W10","next":"NEXT"},{"phase":"2","type":"0","salesman":"AB10","customer":"AC10","next":"NEXT"}]},{"first":"SALESMAN","phase":"3","description":"﻿Предложение решения","dialog":[{"phase":"3","type":"1","salesman":"V14","customer":"W14","next":"NEXT"},{"phase":"3","type":"0","salesman":"AF14,AB14","customer":"AE14","next":"NEXT"}]},{"first":"SALESMAN","phase":"0","description":"﻿Товара нет в WEB-ППО","dialog":[{"phase":"0","type":"1","salesman":"V21","customer":"W21","next":"NEXT"},{"phase":"0","type":"0","salesman":"AD21,AB21","customer":"AE21","next":"NEXT"}]},{"first":"CUSTOMER","phase":"4","description":"﻿Работа с возражениями","dialog":[{"phase":"4","type":"1","salesman":"V25","customer":"W25","next":"NEXT"},{"phase":"4","type":"0","salesman":"AD15,AF15","customer":"","next":"NEXT"}]},{"first":"CUSTOMER","phase":"5","description":"﻿Оформление кредита, шаг 1","dialog":[{"phase":"5","type":"1","salesman":"V31","customer":"W31","next":"NEXT"},{"phase":"5","type":"0","salesman":"AD16-1","customer":"AE32","next":"NEXT"}]},{"first":"SALESMAN","phase":"5","description":"﻿Оформление кредита, шаг 2","dialog":[{"phase":"5","type":"1","salesman":"V32,X32","customer":"W32","next":"NEXT"},{"phase":"5","type":"0","salesman":"","customer":"","next":"NEXT"}]},{"first":"SALESMAN","phase":"6","description":"﻿Завершение сделки, шаг 1","dialog":[{"phase":"6","type":"1","salesman":"V34","customer":"W34","next":"NEXT"},{"phase":"6","type":"0","salesman":"AD34","customer":"AE34","next":"NEXT"},{"phase":"6","type":"1","salesman":"R35","customer":"U34","next":"NEXT"},{"phase":"6","type":"0","salesman":"AF34","customer":"AE34","next":"NEXT"}]},{"first":"SALESMAN","phase":"6","description":"﻿Завершение сделки, шаг 2","dialog":[{"phase":"6","type":"1","salesman":"V35","customer":"W35","next":"NEXT"},{"phase":"6","type":"0","salesman":"Z35","customer":"AA35","next":"NEXT"},{"phase":"6","type":"1","salesman":"T35","customer":"W36","next":"NEXT"},{"phase":"6","type":"0","salesman":"AF35","customer":"AA35","next":"NEXT"}]},{"first":"SALESMAN","phase":"7","description":"﻿Оформление сделки, завершение контакта, шаг 1","dialog":[{"phase":"7","type":"1","salesman":"V36-2","customer":"W38-2","next":"NEXT"},{"phase":"7","type":"0","salesman":"","customer":"","next":"NEXT"}]},{"first":"SALESMAN","phase":"7","description":"﻿Оформление сделки, завершение контакта, шаг 2","dialog":[{"phase":"7","type":"1","salesman":"V39","customer":"U39","next":"NEXT"},{"phase":"7","type":"0","salesman":"","customer":"","next":"NEXT"},{"phase":"7","type":"1","salesman":"T39","customer":"U39","next":"NEXT"},{"phase":"7","type":"0","salesman":"","customer":"","next":"NEXT"}]}]}
